LICENSE
README.md
setup.py
Math/DeterminantZero.py
Math/DiscreteDistribution.py
Math/Distribution.py
Math/Eigenvector.py
Math/Matrix.py
Math/MatrixColumnMismatch.py
Math/MatrixDimensionMismatch.py
Math/MatrixNotPositiveDefinite.py
Math/MatrixNotSquare.py
Math/MatrixNotSymmetric.py
Math/MatrixRowColumnMismatch.py
Math/MatrixRowMismatch.py
Math/Tensor.py
Math/Vector.py
Math/VectorSizeMismatch.py
Math/__init__.py
NlpToolkit_Math.egg-info/PKG-INFO
NlpToolkit_Math.egg-info/SOURCES.txt
NlpToolkit_Math.egg-info/dependency_links.txt
NlpToolkit_Math.egg-info/top_level.txt