Metadata-Version: 2.1
Name: NlpToolkit-Math
Version: 1.0.20
Summary: Math library
Home-page: https://github.com/StarlangSoftware/Math-Py
Author: olcaytaner
Author-email: olcay.yildiz@ozyegin.edu.tr
License: UNKNOWN
Platform: UNKNOWN
